MANIFEST.in
README.txt
setup.py
docs/COPYRIGHT.txt
docs/CREDITS.txt
docs/HISTORY.txt
docs/LICENSE.txt
src/cromlech/__init__.py
src/cromlech.jwt.egg-info/PKG-INFO
src/cromlech.jwt.egg-info/SOURCES.txt
src/cromlech.jwt.egg-info/dependency_links.txt
src/cromlech.jwt.egg-info/namespace_packages.txt
src/cromlech.jwt.egg-info/not-zip-safe
src/cromlech.jwt.egg-info/requires.txt
src/cromlech.jwt.egg-info/top_level.txt
src/cromlech/jwt/__init__.py
src/cromlech/jwt/components.py
src/cromlech/jwt/utils.py
tests/__init__.py
tests/test_jwt.txt