Metadata-Version: 2.1
Name: cromlech.jwt
Version: 0.2.1
Summary: JWT support for Cromlech
Home-page: http://gitweb.dolmen-project.org
Author: Cromlech Team
Author-email: 
License: ZPL
Download-URL: http://pypi.python.org/pypi/cromlech.jwt
Platform: UNKNOWN
Classifier: Environment :: Web Environment
Classifier: Intended Audience :: Developers
Classifier: License :: OSI Approved :: Zope Public License
Classifier: Programming Language :: Python
Provides-Extra: test
